vvlab/__init__.py
vvlab/__version__.py
vvlab/agents/DDPG_base.py
vvlab/agents/DQN_base.py
vvlab/agents/Linear_base.py
vvlab/agents/__init__.py
vvlab/envs/PC_env.py
vvlab/envs/__init__.py
vvlab/envs/findtreasure_env.py
vvlab/envs/maze_env.py
vvlab/envs/PowerControl/PC_env.py
vvlab/envs/PowerControl/PC_env_format_test.py
vvlab/envs/PowerControl/PC_env_origin.py
vvlab/envs/PowerControl/PC_env_unit_test.py
vvlab/envs/PowerControl/__init__.py
vvlab/envs/power_allocation/__init__.py
vvlab/envs/power_allocation/pa_env.py
vvlab/envs/power_allocation/pa_rb_env.py
vvlab/envs/power_allocation/pa_rb_utils.py
vvlab/envs/power_allocation/test_pa_env.py
vvlab/envs/power_allocation/test_pa_rb_env.py
vvlab/logs/__init__.py
vvlab/logs/assamble.py
vvlab/models/__init__.py
vvlab/models/actor_net.py
vvlab/models/critic_net.py
vvlab/models/dqn_net.py
vvlab/utils/OUProcess.py
vvlab/utils/ReplayBuffer.py
vvlab/utils/__init__.py
vvlab/utils/config.py
vvlab/utils/update.py
vvlab-0.2.4.dist-info/LICENCE
vvlab-0.2.4.dist-info/METADATA
vvlab-0.2.4.dist-info/WHEEL
vvlab-0.2.4.dist-info/top_level.txt
vvlab-0.2.4.dist-info/RECORD
